koya_scraper/__init__.py
koya_scraper/koya_scraper.py
koya_scraper-0.0.7.dist-info/LICENSE
koya_scraper-0.0.7.dist-info/METADATA
koya_scraper-0.0.7.dist-info/WHEEL
koya_scraper-0.0.7.dist-info/top_level.txt
koya_scraper-0.0.7.dist-info/RECORD
